Metadata-Version: 2.1
Name: arsenalgear
Version: 1.3.0
Summary: A library containing general purpose Python utils
Home-page: https://justwhit3.github.io/
Author: Gianluca Bianco
Author-email: biancogianluca9@gmail.com
License: MIT
Download-URL: https://github.com/JustWhit3/arsenalgear-py/archive/refs/tags/v1.3.0.zip
Platform: UNKNOWN
Classifier: Development Status :: 4 - Beta
Classifier: Intended Audience :: Developers
Classifier: Topic :: Software Development
Classifier: License :: OSI Approved :: MIT License
Classifier: Programming Language :: Python :: 3
Classifier: Programming Language :: Python :: 3.10
License-File: LICENSE
